streamlit_editorjs_component/__init__.py
streamlit_editorjs_component/frontend/build/asset-manifest.json
streamlit_editorjs_component/frontend/build/favicon.ico
streamlit_editorjs_component/frontend/build/index.html
streamlit_editorjs_component/frontend/build/logo192.png
streamlit_editorjs_component/frontend/build/logo512.png
streamlit_editorjs_component/frontend/build/manifest.json
streamlit_editorjs_component/frontend/build/robots.txt
streamlit_editorjs_component/frontend/build/static/js/main.1a0ad64b.js
streamlit_editorjs_component/frontend/build/static/js/main.1a0ad64b.js.LICENSE.txt
streamlit_editorjs_component/frontend/build/static/js/main.1a0ad64b.js.map
streamlit_editorjs_component/frontend/build/static/js/main.ab7f878a.js
streamlit_editorjs_component/frontend/build/static/js/main.ab7f878a.js.LICENSE.txt
streamlit_editorjs_component/frontend/build/static/js/main.ab7f878a.js.map
streamlit_editorjs_component-0.1.5.dist-info/LICENSE
streamlit_editorjs_component-0.1.5.dist-info/METADATA
streamlit_editorjs_component-0.1.5.dist-info/WHEEL
streamlit_editorjs_component-0.1.5.dist-info/top_level.txt
streamlit_editorjs_component-0.1.5.dist-info/RECORD
