Metadata-Version: 2.1
Name: streamlit-editorjs-component
Version: 0.1.5
Summary: editorjs component for streamlit
Home-page: https://github.com/sanekun/streamlit-editorjs-component
Author: sanekun
Author-email: sanekun@kaist.ac.kr
Requires-Python: >=3.7
License-File: LICENSE
Requires-Dist: streamlit >=1.2
Requires-Dist: jinja2
